fabman/__init__.py
fabman/account.py
fabman/api_key.py
fabman/booking.py
fabman/charge.py
fabman/deleted_object.py
fabman/embedded_list.py
fabman/exceptions.py
fabman/fabman.py
fabman/fabman_object.py
fabman/invoice.py
fabman/job.py
fabman/member.py
fabman/package.py
fabman/paginated_list.py
fabman/payment.py
fabman/requester.py
fabman/resource.py
fabman/resource_log.py
fabman/resource_type.py
fabman/space.py
fabman/training_course.py
fabman/util.py
fabman/webhook.py
fabman-1.2.10.dist-info/LICENSE
fabman-1.2.10.dist-info/METADATA
fabman-1.2.10.dist-info/WHEEL
fabman-1.2.10.dist-info/top_level.txt
fabman-1.2.10.dist-info/RECORD
