Metadata-Version: 2.1
Name: fabman
Version: 1.2.10
Summary: Python wrappers for interacting with the Fabman API
Author: Davin Lawrence
Author-email: Davin Lawrence <davin.lawrence@utexas.edu>, Texas Inventionworks <tiw@utexas.edu>
Project-URL: Homepage, https://github.com/utexas-engr-tiw/fabman-api
Project-URL: Documentation, https://fabman-api.readthedocs.io/en/latest/
Project-URL: Bug Tracker, https://github.com/utexas-engr-tiw/fabman-api/issues
Classifier: Development Status :: 2 - Pre-Alpha
Classifier: Environment :: Console
Classifier: Intended Audience :: Developers
Classifier: Intended Audience :: Education
Classifier: License :: OSI Approved :: MIT License
Classifier: Natural Language :: English
Classifier: Programming Language :: Python :: 3 :: Only
Classifier: Programming Language :: Python :: 3.7
Classifier: Programming Language :: Python :: 3.8
Classifier: Programming Language :: Python :: 3.9
Classifier: Programming Language :: Python :: 3.10
Classifier: Programming Language :: Python :: 3.11
Classifier: Topic :: Education
Requires-Python: >=3.7
License-File: LICENSE
Requires-Dist: requests (>=2.31.0)
Requires-Dist: arrow (>=1.2.3)
Requires-Dist: pytz (==2023.3)
